{
  "totalGames": 18,
  "lastUpdated": "2026-02-02T08:00:00.000Z",
  "categories": {
    "slots": 10,
    "crash-games": 1,
    "table-game": 3,
    "live-casino": 4
  },
  "providers": {
    "Habanero": 3,
    "NetEnt": 2,
    "Pragmatic Play": 2,
    "Red Tiger": 2,
    "Play'n GO": 1,
    "Spribe": 1,
    "Evolution": 4,
    "Microgaming": 2,
    "Felt Gaming": 1
  },
  "games": [
    {
      "id": "hot-hot-betway",
      "name": "Hot Hot Betway",
      "url": "https://www.betway.co.za/lobby/casino-games/slots/hot-hot-betway",
      "category": "slots",
      "provider": "Habanero",
      "gameType": "canvas",
      "hasDemo": true,
      "thumbnailUrl": "",
      "tags": ["popular", "fruit", "classic"],
      "scrapedAt": "2026-01-27T08:00:00.000Z"
    },
    {
      "id": "gonzo-quest-megaways",
      "name": "Gonzo's Quest Megaways",
      "url": "https://www.betway.co.za/lobby/casino-games/slots/gonzo-quest-megaways",
      "category": "slots",
      "provider": "NetEnt",
      "gameType": "canvas",
      "hasDemo": true,
      "thumbnailUrl": "",
      "tags": ["popular", "megaways", "adventure"],
      "scrapedAt": "2026-01-27T08:00:00.000Z"
    },
    {
      "id": "starburst",
      "name": "Starburst",
      "url": "https://www.betway.co.za/lobby/casino-games/slots/starburst",
      "category": "slots",
      "provider": "NetEnt",
      "gameType": "canvas",
      "hasDemo": true,
      "thumbnailUrl": "",
      "tags": ["popular", "classic", "space"],
      "scrapedAt": "2026-01-27T08:00:00.000Z"
    },
    {
      "id": "wealth-inn",
      "name": "Wealth Inn",
      "url": "https://www.betway.co.za/lobby/casino-games/slots/wealth-inn",
      "category": "slots",
      "provider": "Pragmatic Play",
      "gameType": "canvas",
      "hasDemo": true,
      "thumbnailUrl": "",
      "tags": ["popular", "asian"],
      "scrapedAt": "2026-01-27T08:00:00.000Z"
    },
    {
      "id": "777-strike",
      "name": "777 Strike",
      "url": "https://www.betway.co.za/lobby/casino-games/slots/777-strike",
      "category": "slots",
      "provider": "Red Tiger",
      "gameType": "canvas",
      "hasDemo": true,
      "thumbnailUrl": "",
      "tags": ["classic", "777"],
      "scrapedAt": "2026-01-27T08:00:00.000Z"
    },
    {
      "id": "hey-sushi",
      "name": "Hey Sushi",
      "url": "https://www.betway.co.za/lobby/casino-games/slots/hey-sushi",
      "category": "slots",
      "provider": "Habanero",
      "gameType": "canvas",
      "hasDemo": true,
      "thumbnailUrl": "",
      "tags": ["asian", "food"],
      "scrapedAt": "2026-01-27T08:00:00.000Z"
    },
    {
      "id": "book-of-dead",
      "name": "Book of Dead",
      "url": "https://www.betway.co.za/lobby/casino-games/slots/book-of-dead",
      "category": "slots",
      "provider": "Play'n GO",
      "gameType": "canvas",
      "hasDemo": true,
      "thumbnailUrl": "",
      "tags": ["popular", "egypt", "adventure"],
      "scrapedAt": "2026-01-27T08:00:00.000Z"
    },
    {
      "id": "gates-of-olympus",
      "name": "Gates of Olympus",
      "url": "https://www.betway.co.za/lobby/casino-games/slots/gates-of-olympus",
      "category": "slots",
      "provider": "Pragmatic Play",
      "gameType": "canvas",
      "hasDemo": true,
      "thumbnailUrl": "",
      "tags": ["popular", "mythology", "greek"],
      "scrapedAt": "2026-01-27T08:00:00.000Z"
    },
    {
      "id": "disco-beats",
      "name": "Disco Beats",
      "url": "https://www.betway.co.za/lobby/casino-games/slots/disco-beats",
      "category": "slots",
      "provider": "Habanero",
      "gameType": "canvas",
      "hasDemo": true,
      "thumbnailUrl": "",
      "tags": ["music", "retro"],
      "scrapedAt": "2026-01-27T08:00:00.000Z"
    },
    {
      "id": "cash-volt",
      "name": "Cash Volt",
      "url": "https://www.betway.co.za/lobby/casino-games/slots/cash-volt",
      "category": "slots",
      "provider": "Red Tiger",
      "gameType": "canvas",
      "hasDemo": true,
      "thumbnailUrl": "",
      "tags": ["electric", "modern"],
      "scrapedAt": "2026-01-27T08:00:00.000Z"
    },
    {
      "id": "aviator",
      "name": "Aviator",
      "url": "https://www.betway.co.za/lobby/casino-games/aviator",
      "category": "crash-games",
      "provider": "Spribe",
      "gameType": "canvas",
      "hasDemo": true,
      "thumbnailUrl": "",
      "tags": ["popular", "crash", "multiplier"],
      "scrapedAt": "2026-01-27T08:00:00.000Z"
    },
    {
      "id": "blackjack-classic",
      "name": "Classic Blackjack",
      "url": "https://www.betway.co.za/lobby/casino-games/table-games/classic-blackjack",
      "category": "table-game",
      "subType": "blackjack",
      "provider": "Microgaming",
      "gameType": "canvas",
      "hasDemo": true,
      "thumbnailUrl": "",
      "tags": ["table", "blackjack", "cards"],
      "scrapedAt": "2026-02-02T08:00:00.000Z"
    },
    {
      "id": "european-roulette",
      "name": "European Roulette",
      "url": "https://www.betway.co.za/lobby/casino-games/table-games/european-roulette",
      "category": "table-game",
      "subType": "roulette",
      "provider": "Microgaming",
      "gameType": "canvas",
      "hasDemo": true,
      "thumbnailUrl": "",
      "tags": ["table", "roulette", "wheel"],
      "scrapedAt": "2026-02-02T08:00:00.000Z"
    },
    {
      "id": "baccarat",
      "name": "Baccarat",
      "url": "https://www.betway.co.za/lobby/casino-games/table-games/baccarat",
      "category": "table-game",
      "subType": "baccarat",
      "provider": "Felt Gaming",
      "gameType": "canvas",
      "hasDemo": true,
      "thumbnailUrl": "",
      "tags": ["table", "baccarat", "cards"],
      "scrapedAt": "2026-02-02T08:00:00.000Z"
    },
    {
      "id": "live-roulette",
      "name": "Live Roulette",
      "url": "https://www.betway.co.za/Livegames/live-roulette",
      "category": "live-casino",
      "subType": "live-roulette",
      "provider": "Evolution",
      "gameType": "iframe",
      "hasDemo": false,
      "thumbnailUrl": "",
      "tags": ["live", "roulette", "popular"],
      "scrapedAt": "2026-02-02T08:00:00.000Z"
    },
    {
      "id": "live-blackjack",
      "name": "Live Blackjack",
      "url": "https://www.betway.co.za/Livegames/live-blackjack",
      "category": "live-casino",
      "subType": "live-blackjack",
      "provider": "Evolution",
      "gameType": "iframe",
      "hasDemo": false,
      "thumbnailUrl": "",
      "tags": ["live", "blackjack", "popular"],
      "scrapedAt": "2026-02-02T08:00:00.000Z"
    },
    {
      "id": "crazy-time",
      "name": "Crazy Time",
      "url": "https://www.betway.co.za/Livegames/crazy-time",
      "category": "live-casino",
      "subType": "game-show",
      "provider": "Evolution",
      "gameType": "iframe",
      "hasDemo": false,
      "thumbnailUrl": "",
      "tags": ["live", "game-show", "popular"],
      "scrapedAt": "2026-02-02T08:00:00.000Z"
    },
    {
      "id": "mega-ball",
      "name": "Mega Ball",
      "url": "https://www.betway.co.za/Livegames/mega-ball",
      "category": "live-casino",
      "subType": "game-show",
      "provider": "Evolution",
      "gameType": "iframe",
      "hasDemo": false,
      "thumbnailUrl": "",
      "tags": ["live", "game-show", "lottery"],
      "scrapedAt": "2026-02-02T08:00:00.000Z"
    }
  ]
}
